duecredit/__init__.py
duecredit/__main__.py
duecredit/collector.py
duecredit/config.py
duecredit/dueswitch.py
duecredit/entries.py
duecredit/io.py
duecredit/log.py
duecredit/parsers.py
duecredit/stub.py
duecredit/utils.py
duecredit/version.py
duecredit/versions.py
duecredit/cmdline/__init__.py
duecredit/cmdline/cmd_summary.py
duecredit/cmdline/cmd_test.py
duecredit/cmdline/common_args.py
duecredit/cmdline/helpers.py
duecredit/cmdline/main.py
duecredit/injections/__init__.py
duecredit/injections/injector.py
duecredit/injections/mod_biosig.py
duecredit/injections/mod_dipy.py
duecredit/injections/mod_matplotlib.py
duecredit/injections/mod_mdp.py
duecredit/injections/mod_mne.py
duecredit/injections/mod_nibabel.py
duecredit/injections/mod_nipy.py
duecredit/injections/mod_nipype.py
duecredit/injections/mod_numpy.py
duecredit/injections/mod_pandas.py
duecredit/injections/mod_psychopy.py
duecredit/injections/mod_scipy.py
duecredit/injections/mod_skimage.py
duecredit/injections/mod_sklearn.py
duecredit/tests/__init__.py
duecredit/tests/test__main__.py
duecredit/tests/test_api.py
duecredit/tests/test_cmdline.py
duecredit/tests/test_collector.py
duecredit/tests/test_dueswitch.py
duecredit/tests/test_entries.py
duecredit/tests/test_import_doi
duecredit/tests/test_injections.py
duecredit/tests/test_io.py
duecredit/tests/test_utils.py
duecredit/tests/test_versions.py
duecredit/tests/envs/nolxml/lxml.py
duecredit/tests/mod/__init__.py
duecredit/tests/mod/imported.py
duecredit/tests/mod/submod.py
duecredit-0.10.2.dist-info/LICENSE
duecredit-0.10.2.dist-info/METADATA
duecredit-0.10.2.dist-info/WHEEL
duecredit-0.10.2.dist-info/entry_points.txt
duecredit-0.10.2.dist-info/top_level.txt
duecredit-0.10.2.dist-info/RECORD
